sssapi/__init__.py
snowshoe_stamp_sdk-3.0.3.dist-info/LICENSE
snowshoe_stamp_sdk-3.0.3.dist-info/METADATA
snowshoe_stamp_sdk-3.0.3.dist-info/WHEEL
snowshoe_stamp_sdk-3.0.3.dist-info/top_level.txt
snowshoe_stamp_sdk-3.0.3.dist-info/RECORD
