Metadata-Version: 2.1
Name: snowshoe-stamp-sdk
Version: 3.0.3
Summary: SnowShoeStamp Client Api Library
Home-page: https://github.com/snowshoestamp/snowshoe-sdk-python
Author: Snowshoe Stamps
Author-email: engineering@snowshoestamp.com
License: UNKNOWN
Platform: UNKNOWN
Classifier: Programming Language :: Python :: 2.7
Classifier: License :: OSI Approved :: MIT License
Classifier: Operating System :: OS Independent
Requires-Python: >=2.7
